splink/__init__.py
splink/blocking_analysis.py
splink/blocking_rule_library.py
splink/clustering.py
splink/comparison_level_library.py
splink/comparison_library.py
splink/datasets.py
splink/exploratory.py
splink/py.typed
splink/backends/athena.py
splink/backends/duckdb.py
splink/backends/postgres.py
splink/backends/spark.py
splink/backends/sqlite.py
splink/internals/__init__.py
splink/internals/accuracy.py
splink/internals/block_from_labels.py
splink/internals/blocking.py
splink/internals/blocking_analysis.py
splink/internals/blocking_rule_creator.py
splink/internals/blocking_rule_creator_utils.py
splink/internals/blocking_rule_library.py
splink/internals/cache_dict_with_logging.py
splink/internals/charts.py
splink/internals/cluster_studio.py
splink/internals/clustering.py
splink/internals/column_expression.py
splink/internals/comparison.py
splink/internals/comparison_creator.py
splink/internals/comparison_level.py
splink/internals/comparison_level_composition.py
splink/internals/comparison_level_creator.py
splink/internals/comparison_level_library.py
splink/internals/comparison_level_sql.py
splink/internals/comparison_library.py
splink/internals/comparison_vector_distribution.py
splink/internals/comparison_vector_values.py
splink/internals/completeness.py
splink/internals/connected_components.py
splink/internals/constants.py
splink/internals/cost_of_blocking_rules.py
splink/internals/database_api.py
splink/internals/default_from_jsonschema.py
splink/internals/dialects.py
splink/internals/edge_metrics.py
splink/internals/em_training_session.py
splink/internals/estimate_u.py
splink/internals/exceptions.py
splink/internals/expectation_maximisation.py
splink/internals/find_brs_with_comparison_counts_below_threshold.py
splink/internals/find_matches_to_new_records.py
splink/internals/graph_metrics.py
splink/internals/input_column.py
splink/internals/labelling_tool.py
splink/internals/linker.py
splink/internals/logging_messages.py
splink/internals/lower_id_on_lhs.py
splink-4.0.12.dist-info/METADATA
splink-4.0.12.dist-info/WHEEL
splink-4.0.12.dist-info/licenses/LICENSE
splink-4.0.12.dist-info/RECORD
