Metadata-Version: 2.4
Name: splink
Version: 4.0.12
Summary: Fast probabilistic data linkage at scale
Project-URL: Homepage, https://github.com/moj-analytical-services/splink
Project-URL: Repository, https://github.com/moj-analytical-services/splink
Author: Sam Lindsay, Theodore Manassis, Tom Hepworth, Andy Bond, Ross Kennedy
Author-email: Robin Linacre <robinlinacre@hotmail.com>
License-Expression: MIT
License-File: LICENSE
Requires-Python: <4.0.0,>=3.9.0
Requires-Dist: altair>=5.0.1
Requires-Dist: duckdb>=0.9.2
Requires-Dist: igraph>=0.11.2
Requires-Dist: jinja2>=3.0.3
Requires-Dist: numpy>=1.19.3
Requires-Dist: pandas>=1.3.5
Requires-Dist: sqlglot>=17.6.0
Provides-Extra: athena
Requires-Dist: awswrangler; extra == 'athena'
Provides-Extra: postgres
Requires-Dist: psycopg2-binary>=2.9.0; extra == 'postgres'
Requires-Dist: sqlalchemy>=2.0.0; extra == 'postgres'
Provides-Extra: pyspark
Requires-Dist: pyspark>=3.5.0; extra == 'pyspark'
Provides-Extra: spark
Requires-Dist: pyspark>=3.5.0; extra == 'spark'
